{
    "name": "Competence",
    "fields": [
        {
            "fieldName": "compName",
            "fieldType": "Integer",
            "fieldValidateRules": [
                "required"
            ]
        },
        {
            "fieldName": "compDesc",
            "fieldType": "String"
        }
    ],
    "relationships": [
        {
            "relationshipName": "competenceAplication",
            "otherEntityName": "competenceAplication",
            "relationshipType": "many-to-one",
            "otherEntityField": "id"
        }
    ],
    "changelogDate": "20181231120223",
    "entityTableName": "competence",
    "dto": "no",
    "pagination": "pagination",
    "service": "serviceImpl",
    "jpaMetamodelFiltering": false,
    "fluentMethods": true,
    "clientRootFolder": "",
    "applications": "*"
}